zview_cli.py
zview-0.5.1.dist-info/licenses/LICENSE
zview-0.5.1.dist-info/METADATA
zview-0.5.1.dist-info/WHEEL
zview-0.5.1.dist-info/entry_points.txt
zview-0.5.1.dist-info/top_level.txt
zview-0.5.1.dist-info/RECORD
