Metadata-Version: 2.4
Name: zview
Version: 0.5.1
Summary: ZView, a Zephyr RTOS runtime visualizer
Author-email: Paulo Santos <pauloxrms@gmail.com>
License-Expression: Apache-2.0
Project-URL: Homepage, https://github.com/wkhadgar/zview
Project-URL: Issues, https://github.com/wkhadgar/zview/issues
Keywords: Zephyr,RTOS,Zephyr RTOS,threads,stacks,heaps,analyser,ZView,tooling,module
Classifier: Development Status :: 3 - Alpha
Classifier: Intended Audience :: Developers
Classifier: Programming Language :: Python :: 3
Classifier: Topic :: Software Development :: Embedded Systems
License-File: LICENSE
Requires-Dist: PyYAML
Requires-Dist: pyelftools
Requires-Dist: pyocd
Requires-Dist: pylink-square
Dynamic: license-file
